aws_s3_mcp/__init__.py
aws_s3_mcp/__main__.py
aws_s3_mcp/app.py
aws_s3_mcp/config.py
aws_s3_mcp/services/__init__.py
aws_s3_mcp/services/s3_service.py
aws_s3_mcp/tools/__init__.py
aws_s3_mcp/tools/s3_tools.py
aws_s3_mcp-0.1.3.dist-info/METADATA
aws_s3_mcp-0.1.3.dist-info/WHEEL
aws_s3_mcp-0.1.3.dist-info/entry_points.txt
aws_s3_mcp-0.1.3.dist-info/RECORD
