Metadata-Version: 2.4
Name: aws-s3-mcp
Version: 0.1.3
Summary: MCP server for AWS S3 storage access
Author-email: Arclio Team <info@arclio.com>
License: MIT
Requires-Python: >=3.10
Requires-Dist: aioboto3>=13.2.0
Requires-Dist: mcp>=1.7.0
Requires-Dist: pypdf>=5.1.0
Requires-Dist: python-dotenv>=1.0.1
Provides-Extra: dev
